<?xml version="1.0" encoding="utf-8" standalone="yes"?>
<Gesture Name="half_note~09" Subject="10" InputType="stylus" Speed="MEDIUM" NumPts="146">
	<Stroke index="1">
		<Point X="89" Y="4" T="1302127062748" Pressure="128" />
		<Point X="91" Y="7" T="1302127062748" Pressure="128" />
		<Point X="90" Y="9" T="1302127062748" Pressure="128" />
		<Point X="90" Y="10" T="1302127062764" Pressure="128" />
		<Point X="90" Y="11" T="1302127062764" Pressure="128" />
		<Point X="90" Y="12" T="1302127062795" Pressure="128" />
		<Point X="89" Y="13" T="1302127062795" Pressure="128" />
		<Point X="89" Y="15" T="1302127062795" Pressure="128" />
		<Point X="89" Y="16" T="1302127062810" Pressure="128" />
		<Point X="89" Y="17" T="1302127062810" Pressure="128" />
		<Point X="88" Y="18" T="1302127062826" Pressure="128" />
		<Point X="88" Y="19" T="1302127062842" Pressure="128" />
		<Point X="88" Y="20" T="1302127062842" Pressure="128" />
		<Point X="87" Y="21" T="1302127062842" Pressure="128" />
		<Point X="87" Y="22" T="1302127062857" Pressure="128" />
		<Point X="87" Y="24" T="1302127062857" Pressure="128" />
		<Point X="86" Y="25" T="1302127062873" Pressure="128" />
		<Point X="86" Y="26" T="1302127062873" Pressure="128" />
		<Point X="86" Y="27" T="1302127062873" Pressure="128" />
		<Point X="85" Y="28" T="1302127062888" Pressure="128" />
		<Point X="85" Y="30" T="1302127062904" Pressure="128" />
		<Point X="85" Y="31" T="1302127062904" Pressure="128" />
		<Point X="85" Y="32" T="1302127062904" Pressure="128" />
		<Point X="85" Y="33" T="1302127062920" Pressure="128" />
		<Point X="85" Y="35" T="1302127062920" Pressure="128" />
		<Point X="85" Y="36" T="1302127062935" Pressure="128" />
		<Point X="85" Y="37" T="1302127062951" Pressure="128" />
		<Point X="85" Y="38" T="1302127062951" Pressure="128" />
		<Point X="85" Y="40" T="1302127062951" Pressure="128" />
		<Point X="85" Y="41" T="1302127062966" Pressure="128" />
		<Point X="85" Y="42" T="1302127062966" Pressure="128" />
		<Point X="84" Y="44" T="1302127062982" Pressure="128" />
		<Point X="84" Y="45" T="1302127062982" Pressure="128" />
		<Point X="84" Y="47" T="1302127062998" Pressure="128" />
		<Point X="84" Y="48" T="1302127062998" Pressure="128" />
		<Point X="84" Y="50" T="1302127063013" Pressure="128" />
		<Point X="84" Y="51" T="1302127063029" Pressure="128" />
		<Point X="84" Y="53" T="1302127063029" Pressure="128" />
		<Point X="84" Y="55" T="1302127063029" Pressure="128" />
		<Point X="84" Y="56" T="1302127063044" Pressure="128" />
		<Point X="84" Y="58" T="1302127063044" Pressure="128" />
		<Point X="84" Y="60" T="1302127063060" Pressure="128" />
		<Point X="84" Y="62" T="1302127063076" Pressure="128" />
		<Point X="84" Y="63" T="1302127063076" Pressure="128" />
		<Point X="84" Y="65" T="1302127063076" Pressure="128" />
		<Point X="83" Y="67" T="1302127063091" Pressure="128" />
		<Point X="83" Y="69" T="1302127063091" Pressure="128" />
		<Point X="83" Y="70" T="1302127063107" Pressure="128" />
		<Point X="83" Y="72" T="1302127063107" Pressure="128" />
		<Point X="83" Y="73" T="1302127063107" Pressure="128" />
		<Point X="82" Y="75" T="1302127063122" Pressure="128" />
		<Point X="82" Y="77" T="1302127063138" Pressure="128" />
		<Point X="82" Y="78" T="1302127063138" Pressure="128" />
		<Point X="82" Y="80" T="1302127063138" Pressure="128" />
		<Point X="82" Y="81" T="1302127063154" Pressure="128" />
		<Point X="81" Y="83" T="1302127063154" Pressure="128" />
		<Point X="81" Y="84" T="1302127063169" Pressure="128" />
		<Point X="81" Y="86" T="1302127063185" Pressure="128" />
		<Point X="81" Y="87" T="1302127063185" Pressure="128" />
		<Point X="81" Y="88" T="1302127063185" Pressure="128" />
		<Point X="81" Y="90" T="1302127063200" Pressure="128" />
		<Point X="81" Y="91" T="1302127063200" Pressure="128" />
		<Point X="81" Y="92" T="1302127063216" Pressure="128" />
		<Point X="81" Y="94" T="1302127063216" Pressure="128" />
		<Point X="81" Y="95" T="1302127063232" Pressure="128" />
		<Point X="81" Y="96" T="1302127063232" Pressure="128" />
		<Point X="81" Y="98" T="1302127063247" Pressure="128" />
		<Point X="81" Y="99" T="1302127063263" Pressure="128" />
		<Point X="80" Y="100" T="1302127063263" Pressure="128" />
		<Point X="80" Y="101" T="1302127063263" Pressure="128" />
		<Point X="80" Y="102" T="1302127063278" Pressure="128" />
		<Point X="80" Y="103" T="1302127063278" Pressure="128" />
		<Point X="80" Y="104" T="1302127063294" Pressure="128" />
		<Point X="80" Y="105" T="1302127063294" Pressure="128" />
		<Point X="80" Y="106" T="1302127063310" Pressure="128" />
		<Point X="79" Y="107" T="1302127063310" Pressure="128" />
		<Point X="79" Y="108" T="1302127063325" Pressure="128" />
		<Point X="79" Y="109" T="1302127063325" Pressure="128" />
		<Point X="79" Y="110" T="1302127063325" Pressure="128" />
		<Point X="79" Y="111" T="1302127063341" Pressure="128" />
		<Point X="78" Y="111" T="1302127063372" Pressure="128" />
		<Point X="78" Y="111" T="1302127063372" Pressure="128" />
	</Stroke>
	<Stroke index="2">
		<Point X="73" Y="111" T="1302127063762" Pressure="128" />
		<Point X="70" Y="111" T="1302127063762" Pressure="128" />
		<Point X="62" Y="113" T="1302127063762" Pressure="128" />
		<Point X="60" Y="115" T="1302127063778" Pressure="128" />
		<Point X="59" Y="116" T="1302127063793" Pressure="128" />
		<Point X="58" Y="116" T="1302127063793" Pressure="128" />
		<Point X="57" Y="117" T="1302127063793" Pressure="128" />
		<Point X="56" Y="118" T="1302127063809" Pressure="128" />
		<Point X="55" Y="119" T="1302127063824" Pressure="128" />
		<Point X="55" Y="120" T="1302127063840" Pressure="128" />
		<Point X="55" Y="121" T="1302127063840" Pressure="128" />
		<Point X="54" Y="122" T="1302127063840" Pressure="128" />
		<Point X="54" Y="123" T="1302127063856" Pressure="128" />
		<Point X="54" Y="124" T="1302127063856" Pressure="128" />
		<Point X="54" Y="125" T="1302127063871" Pressure="128" />
		<Point X="54" Y="126" T="1302127063887" Pressure="128" />
		<Point X="54" Y="127" T="1302127063887" Pressure="128" />
		<Point X="54" Y="129" T="1302127063887" Pressure="128" />
		<Point X="54" Y="130" T="1302127063902" Pressure="128" />
		<Point X="55" Y="131" T="1302127063902" Pressure="128" />
		<Point X="55" Y="132" T="1302127063918" Pressure="128" />
		<Point X="56" Y="133" T="1302127063918" Pressure="128" />
		<Point X="56" Y="134" T="1302127063918" Pressure="128" />
		<Point X="57" Y="134" T="1302127063934" Pressure="128" />
		<Point X="58" Y="135" T="1302127063949" Pressure="128" />
		<Point X="59" Y="136" T="1302127063949" Pressure="128" />
		<Point X="60" Y="137" T="1302127063949" Pressure="128" />
		<Point X="61" Y="138" T="1302127063965" Pressure="128" />
		<Point X="62" Y="138" T="1302127063965" Pressure="128" />
		<Point X="63" Y="139" T="1302127063980" Pressure="128" />
		<Point X="64" Y="139" T="1302127063996" Pressure="128" />
		<Point X="66" Y="140" T="1302127063996" Pressure="128" />
		<Point X="67" Y="140" T="1302127063996" Pressure="128" />
		<Point X="69" Y="140" T="1302127064012" Pressure="128" />
		<Point X="70" Y="140" T="1302127064012" Pressure="128" />
		<Point X="72" Y="140" T="1302127064027" Pressure="128" />
		<Point X="73" Y="140" T="1302127064027" Pressure="128" />
		<Point X="75" Y="140" T="1302127064043" Pressure="128" />
		<Point X="77" Y="139" T="1302127064043" Pressure="128" />
		<Point X="78" Y="139" T="1302127064058" Pressure="128" />
		<Point X="80" Y="138" T="1302127064074" Pressure="128" />
		<Point X="81" Y="137" T="1302127064074" Pressure="128" />
		<Point X="83" Y="136" T="1302127064074" Pressure="128" />
		<Point X="84" Y="135" T="1302127064090" Pressure="128" />
		<Point X="85" Y="134" T="1302127064090" Pressure="128" />
		<Point X="86" Y="133" T="1302127064121" Pressure="128" />
		<Point X="86" Y="132" T="1302127064121" Pressure="128" />
		<Point X="86" Y="131" T="1302127064121" Pressure="128" />
		<Point X="86" Y="130" T="1302127064136" Pressure="128" />
		<Point X="86" Y="129" T="1302127064136" Pressure="128" />
		<Point X="86" Y="127" T="1302127064152" Pressure="128" />
		<Point X="86" Y="126" T="1302127064152" Pressure="128" />
		<Point X="85" Y="125" T="1302127064152" Pressure="128" />
		<Point X="85" Y="124" T="1302127064168" Pressure="128" />
		<Point X="85" Y="123" T="1302127064183" Pressure="128" />
		<Point X="84" Y="122" T="1302127064183" Pressure="128" />
		<Point X="83" Y="121" T="1302127064183" Pressure="128" />
		<Point X="83" Y="120" T="1302127064199" Pressure="128" />
		<Point X="82" Y="119" T="1302127064199" Pressure="128" />
		<Point X="82" Y="118" T="1302127064214" Pressure="128" />
		<Point X="81" Y="117" T="1302127064230" Pressure="128" />
		<Point X="81" Y="116" T="1302127064230" Pressure="128" />
		<Point X="81" Y="115" T="1302127064246" Pressure="128" />
		<Point X="81" Y="115" T="1302127064277" Pressure="128" />
	</Stroke>
</Gesture>
